Workbook
Name F0_in: Inputs!$D$8
Name FC_AMT: Inputs!$D$6
Name K_CALL: Inputs!$D$12
Name K_PUT: Inputs!$D$11
Name PREM_CALL: Inputs!$D$14
Name PREM_PUT: Inputs!$D$13
Name R_FC: Inputs!$D$10
Name R_USD: Inputs!$D$9
Name S0_in: Inputs!$D$7
Name T_DAYS: Inputs!$D$15

Sheet Cover
A1: U.S. Tech Services Firm — FX Transaction Hedge Model
A4: Author | B4: Timmy Vuong | D4: MODEL STATUS | E4: =Checks!B3 -> PASS | H4: Data Provenance
A5: Course | B5: FIN 321 International Finance & Securities | H5: Scenario | I5: Assigned | J5: Scenario 3 course file
A6: Scenario | B6: Scenario 3 — U.S. Tech Services Firm | H6: Stage 2 spec | I6: Committed | J6: GitHub specification URL in Notes & Assumptions
A7: Version | B7: 1.0 — Stage 3 Build | H7: Market data | I7: Indicative | J7: Replace with sourced live values in Stage 4
A8: Build date | B8: 2026-08-08 | H8: Model date | I8: 2026-08-08 | J8: Pacific/Honolulu
A9: Functional currency | B9: USD
A10: Exposure | B10: EUR 12,500,000 receivable in 365 days
A12: Base-Case Strategy Comparison
A13: Strategy | B13: USD Proceeds | C13: Effective Rate | D13: Explicit Cost | E13: Difference vs No Hedge | F13: Interpretation
A14: No Hedge | B14: =FC_AMT*S0_in -> 13500000 | C14: =B14/FC_AMT -> 1.08 | D14: =0 -> 0 | E14: =B14-B14 -> 0 | F14: Fully exposed to settlement EUR/USD.
A15: Forward | B15: ='Forward Hedge'!B10 -> 13637500 | C15: =B15/FC_AMT -> 1.091 | D15: =0 -> 0 | E15: =B15-B14 -> 137500 | F15: Locks the assigned forward rate.
A16: Money Market | B16: ='Money Market'!C9 -> 13637500 | C16: =B16/FC_AMT -> 1.091 | D16: =0 -> 0 | E16: =B16-B14 -> 137500 | F16: Locks proceeds through borrow-convert-invest steps.
A17: EUR Put | B17: ='Option Hedge'!B12 -> 13287500 | C17: =B17/FC_AMT -> 1.063 | D17: =FC_AMT*PREM_PUT -> 212500 | E17: =B17-B14 -> -212500 | F17: Provides a downside floor while preserving upside.
A18: EUR Call (Reference) | B18: ='Option Hedge'!B19 -> 13225000 | C18: =B18/FC_AMT -> 1.058 | D18: =FC_AMT*PREM_CALL -> 275000 | E18: =B18-B14 -> -275000 | F18: Reference payoff; does not protect a EUR receivable from euro weakness.
A20: PRELIMINARY STAGE 3 MODEL — The workbook is fully formula-driven, but S0_in, R_USD, R_FC, K_PUT, and K_CALL are indicative assumptions. Replace and source them in Stage 4 before making a hedge recommendation.

Sheet Legend & Key
A1: Legend & Key
A4: Workbook Color Convention
A5: Color | B5: Meaning | C5: Applied To
A6: Yellow | B6: Inputs | C6: Editable named input cells
A7: Blue | B7: Assumptions | C7: Model conventions and control assumptions
A8: Green | B8: Formulas | C8: Intermediate formula-driven calculations
A9: Gray | B9: Outputs | C9: Decision outputs and status cells
A11: Required Named Ranges
A12: Name | B12: Meaning | C12: Current Value | D12: Attached Cell
A13: FC_AMT | B13: Foreign-currency amount | C13: =FC_AMT -> 12500000 | D13: Inputs!D6
A14: S0_in | B14: Spot EUR/USD | C14: =S0_in -> 1.08 | D14: Inputs!D7
A15: F0_in | B15: Forward EUR/USD | C15: =F0_in -> 1.091 | D15: Inputs!D8
A16: R_USD | B16: USD annual rate | C16: =R_USD -> 0.045 | D16: Inputs!D9
A17: R_FC | B17: EUR annual rate | C17: =R_FC -> 0.034601911 | D17: Inputs!D10
A18: K_PUT | B18: EUR put strike | C18: =K_PUT -> 1.07 | D18: Inputs!D11
A19: K_CALL | B19: EUR call strike | C19: =K_CALL -> 1.11 | D19: Inputs!D12
A20: PREM_PUT | B20: Put premium per EUR | C20: =PREM_PUT -> 0.017 | D20: Inputs!D13
A21: PREM_CALL | B21: Call premium per EUR | C21: =PREM_CALL -> 0.022 | D21: Inputs!D14
A22: T_DAYS | B22: Settlement days | C22: =T_DAYS -> 365 | D22: Inputs!D15

Sheet Inputs
A1: FX Hedging Model — Inputs
A3: INDICATIVE STAGE 3 INPUTS — replace all market assumptions with live, sourced data in Stage 4
A5: Named Range | B5: Description | C5: Unit | D5: Input Value | E5: Status | F5: Source / Rationale
A6: FC_AMT | B6: Foreign-currency receivable | C6: EUR | D6: 12500000 | E6: Assigned scenario | F6: Scenario 3 contract amount
A7: S0_in | B7: Current EUR/USD spot rate | C7: USD per EUR | D7: 1.08 | E7: Indicative | F7: Stage 3 modeling assumption; replace in Stage 4
A8: F0_in | B8: One-year EUR/USD forward rate | C8: USD per EUR | D8: 1.091 | E8: Assigned / indicative | F8: Scenario 3 forward quote; replace with live Stage 4 quote
A9: R_USD | B9: Annual USD interest rate | C9: Decimal annual rate | D9: 0.045 | E9: Indicative | F9: Stage 3 modeling assumption
A10: R_FC | B10: Annual EUR interest rate | C10: Decimal annual rate | D10: 0.034601911 | E10: Indicative / calibrated | F10: Calibrated to S0_in, R_USD, and F0_in for parity demonstration
A11: K_PUT | B11: EUR put-option strike rate | C11: USD per EUR | D11: 1.07 | E11: Indicative | F11: Near-the-money illustrative strike; replace in Stage 4
A12: K_CALL | B12: EUR call-option strike rate | C12: USD per EUR | D12: 1.11 | E12: Indicative | F12: Illustrative call strike; replace in Stage 4
A13: PREM_PUT | B13: EUR put-option premium | C13: USD per EUR | D13: 0.017 | E13: Assigned / indicative | F13: Scenario 3 option premium
A14: PREM_CALL | B14: EUR call-option premium | C14: USD per EUR | D14: 0.022 | E14: Assigned / indicative | F14: Scenario 3 option premium
A15: T_DAYS | B15: Days until settlement | C15: Days | D15: 365 | E15: Assigned scenario | F15: Contract settlement timing

Sheet Forward Hedge
A1: Forward Hedge
A4: Inputs and Calculation
A5: Line Item | B5: Value | C5: Unit
A6: Foreign-currency amount | B6: =FC_AMT -> 12500000 | C6: EUR
A7: Forward rate | B7: =F0_in -> 1.091 | C7: USD per EUR
A8: Settlement days | B8: =T_DAYS -> 365 | C8: Days
A10: USD proceeds | B10: =FC_AMT*F0_in -> 13637500 | C10: USD
A11: Effective conversion rate | B11: =B10/FC_AMT -> 1.091 | C11: USD per EUR
A13: The forward locks the USD conversion rate and removes downside from a weaker euro. The trade-off is that the firm cannot benefit if the euro strengthens above F0_in.

Sheet Money Market
A1: Money-Market Hedge
A4: Three-Step Hedge Calculation
A5: Step | B5: Calculation | C5: Value | D5: Unit
A6: Time basis | B6: T_DAYS / 360 | C6: =T_DAYS/360 -> 1.0138889 | D6: Years
A7: 1. Borrow EUR | B7: FC_AMT / (1 + R_FC × T_DAYS / 360) | C7: =FC_AMT/(1+R_FC*T_DAYS/360) -> 12076332 | D7: EUR
A8: 2. Convert to USD | B8: EUR borrowed × S0_in | C8: =C7*S0_in -> 13042439 | D8: USD
A9: 3. Invest USD | B9: USD now × (1 + R_USD × T_DAYS / 360) | C9: =C8*(1+R_USD*T_DAYS/360) -> 13637500 | D9: USD
A11: Implied forward | B11: S0_in × (1 + R_USD × t) / (1 + R_FC × t) | C11: =S0_in*(1+R_USD*T_DAYS/360)/(1+R_FC*T_DAYS/360) -> 1.091 | D11: USD per EUR
A12: Quoted forward | B12: F0_in | C12: =F0_in -> 1.091 | D12: USD per EUR
A13: Rate difference | B13: Implied forward − F0_in | C13: =C11-C12 -> 0 | D13: USD per EUR
A14: Effective conversion rate | B14: USD maturity proceeds / FC_AMT | C14: =C9/FC_AMT -> 1.091 | D14: USD per EUR
A16: Borrow the present value of the EUR receivable, convert it at the spot rate, invest the USD, and use the future EUR receipt to repay the euro loan. The calibrated indicative rates make the parity demonstration reconcile to the assigned forward quote.

Sheet Option Hedge
A1: Option Hedge
A4: Settlement spot (S_T)
A5: Base case | B5: =S0_in -> 1.08
A7: EUR Put — Relevant Downside Hedge for the Receivable
A8: Line Item | B8: Value | C8: Unit
A9: Protected conversion rate | B9: =MAX(B5,K_PUT) -> 1.08 | C9: USD per EUR
A10: Put intrinsic value per EUR | B10: =MAX(K_PUT-B5,0) -> 0 | C10: USD per EUR
A11: Premium cost | B11: =FC_AMT*PREM_PUT -> 212500 | C11: USD
A12: USD proceeds after premium | B12: =FC_AMT*MAX(B5,K_PUT)-FC_AMT*PREM_PUT -> 13287500 | C12: USD
A13: Effective conversion rate | B13: =B12/FC_AMT -> 1.063 | C13: USD per EUR
A15: EUR Call — Reference Payoff Required by the Build Contract
A16: Line Item | B16: Value | C16: Unit
A17: Call intrinsic value per EUR | B17: =MAX(B5-K_CALL,0) -> 0 | C17: USD per EUR
A18: Premium cost | B18: =FC_AMT*PREM_CALL -> 275000 | C18: USD
A19: Total USD proceeds including receivable | B19: =FC_AMT*B5+FC_AMT*MAX(B5-K_CALL,0)-FC_AMT*PREM_CALL -> 13225000 | C19: USD
A20: Effective conversion rate | B20: =B19/FC_AMT -> 1.058 | C20: USD per EUR
A22: For a EUR receivable, the put provides downside protection while preserving upside. A purchased EUR call does not protect against euro weakness; it is included as a clearly labeled reference strategy because Stage 3 requires both put and call payoffs.

Sheet Sensitivity
A1: Sensitivity Analysis — USD Proceeds by Settlement EUR/USD
A3: Formula-driven scenarios from 95% to 105% of S0_in in one-percentage-point increments
A5: Multiplier | B5: Settlement S_T | C5: No Hedge | D5: Forward | E5: Money Market | F5: EUR Put | G5: EUR Call (Reference) | H5: Chart label
A6: ='Notes & Assumptions'!B12 -> 0.95 | B6: =A6*S0_in -> 1.026 | C6: =FC_AMT*B6 -> 12825000 | D6: ='Forward Hedge'!$B$10 -> 13637500 | E6: ='Money Market'!$C$9 -> 13637500 | F6: =FC_AMT*MAX(B6,K_PUT)-FC_AMT*PREM_PUT -> 13162500 | G6: =FC_AMT*B6+FC_AMT*MAX(B6-K_CALL,0)-FC_AMT*PREM_CALL -> 12550000 | H6: =TEXT(A6,"0%") -> 95%
A7: =A6+'Notes & Assumptions'!B13 -> 0.96 | B7: =A7*S0_in -> 1.0368 | C7: =FC_AMT*B7 -> 12960000 | D7: ='Forward Hedge'!$B$10 -> 13637500 | E7: ='Money Market'!$C$9 -> 13637500 | F7: =FC_AMT*MAX(B7,K_PUT)-FC_AMT*PREM_PUT -> 13162500 | G7: =FC_AMT*B7+FC_AMT*MAX(B7-K_CALL,0)-FC_AMT*PREM_CALL -> 12685000 | H7: =TEXT(A7,"0%") -> 96%
A8: =A7+'Notes & Assumptions'!B13 -> 0.97 | B8: =A8*S0_in -> 1.0476 | C8: =FC_AMT*B8 -> 13095000 | D8: ='Forward Hedge'!$B$10 -> 13637500 | E8: ='Money Market'!$C$9 -> 13637500 | F8: =FC_AMT*MAX(B8,K_PUT)-FC_AMT*PREM_PUT -> 13162500 | G8: =FC_AMT*B8+FC_AMT*MAX(B8-K_CALL,0)-FC_AMT*PREM_CALL -> 12820000 | H8: =TEXT(A8,"0%") -> 97%
A9: =A8+'Notes & Assumptions'!B13 -> 0.98 | B9: =A9*S0_in -> 1.0584 | C9: =FC_AMT*B9 -> 13230000 | D9: ='Forward Hedge'!$B$10 -> 13637500 | E9: ='Money Market'!$C$9 -> 13637500 | F9: =FC_AMT*MAX(B9,K_PUT)-FC_AMT*PREM_PUT -> 13162500 | G9: =FC_AMT*B9+FC_AMT*MAX(B9-K_CALL,0)-FC_AMT*PREM_CALL -> 12955000 | H9: =TEXT(A9,"0%") -> 98%
A10: =A9+'Notes & Assumptions'!B13 -> 0.99 | B10: =A10*S0_in -> 1.0692 | C10: =FC_AMT*B10 -> 13365000 | D10: ='Forward Hedge'!$B$10 -> 13637500 | E10: ='Money Market'!$C$9 -> 13637500 | F10: =FC_AMT*MAX(B10,K_PUT)-FC_AMT*PREM_PUT -> 13162500 | G10: =FC_AMT*B10+FC_AMT*MAX(B10-K_CALL,0)-FC_AMT*PREM_CALL -> 13090000 | H10: =TEXT(A10,"0%") -> 99%
A11: =A10+'Notes & Assumptions'!B13 -> 1 | B11: =A11*S0_in -> 1.08 | C11: =FC_AMT*B11 -> 13500000 | D11: ='Forward Hedge'!$B$10 -> 13637500 | E11: ='Money Market'!$C$9 -> 13637500 | F11: =FC_AMT*MAX(B11,K_PUT)-FC_AMT*PREM_PUT -> 13287500 | G11: =FC_AMT*B11+FC_AMT*MAX(B11-K_CALL,0)-FC_AMT*PREM_CALL -> 13225000 | H11: =TEXT(A11,"0%") -> 100%
A12: =A11+'Notes & Assumptions'!B13 -> 1.01 | B12: =A12*S0_in -> 1.0908 | C12: =FC_AMT*B12 -> 13635000 | D12: ='Forward Hedge'!$B$10 -> 13637500 | E12: ='Money Market'!$C$9 -> 13637500 | F12: =FC_AMT*MAX(B12,K_PUT)-FC_AMT*PREM_PUT -> 13422500 | G12: =FC_AMT*B12+FC_AMT*MAX(B12-K_CALL,0)-FC_AMT*PREM_CALL -> 13360000 | H12: =TEXT(A12,"0%") -> 101%
A13: =A12+'Notes & Assumptions'!B13 -> 1.02 | B13: =A13*S0_in -> 1.1016 | C13: =FC_AMT*B13 -> 13770000 | D13: ='Forward Hedge'!$B$10 -> 13637500 | E13: ='Money Market'!$C$9 -> 13637500 | F13: =FC_AMT*MAX(B13,K_PUT)-FC_AMT*PREM_PUT -> 13557500 | G13: =FC_AMT*B13+FC_AMT*MAX(B13-K_CALL,0)-FC_AMT*PREM_CALL -> 13495000 | H13: =TEXT(A13,"0%") -> 102%
A14: =A13+'Notes & Assumptions'!B13 -> 1.03 | B14: =A14*S0_in -> 1.1124 | C14: =FC_AMT*B14 -> 13905000 | D14: ='Forward Hedge'!$B$10 -> 13637500 | E14: ='Money Market'!$C$9 -> 13637500 | F14: =FC_AMT*MAX(B14,K_PUT)-FC_AMT*PREM_PUT -> 13692500 | G14: =FC_AMT*B14+FC_AMT*MAX(B14-K_CALL,0)-FC_AMT*PREM_CALL -> 13660000 | H14: =TEXT(A14,"0%") -> 103%
A15: =A14+'Notes & Assumptions'!B13 -> 1.04 | B15: =A15*S0_in -> 1.1232 | C15: =FC_AMT*B15 -> 14040000 | D15: ='Forward Hedge'!$B$10 -> 13637500 | E15: ='Money Market'!$C$9 -> 13637500 | F15: =FC_AMT*MAX(B15,K_PUT)-FC_AMT*PREM_PUT -> 13827500 | G15: =FC_AMT*B15+FC_AMT*MAX(B15-K_CALL,0)-FC_AMT*PREM_CALL -> 13930000 | H15: =TEXT(A15,"0%") -> 104%
A16: =A15+'Notes & Assumptions'!B13 -> 1.05 | B16: =A16*S0_in -> 1.134 | C16: =FC_AMT*B16 -> 14175000 | D16: ='Forward Hedge'!$B$10 -> 13637500 | E16: ='Money Market'!$C$9 -> 13637500 | F16: =FC_AMT*MAX(B16,K_PUT)-FC_AMT*PREM_PUT -> 13962500 | G16: =FC_AMT*B16+FC_AMT*MAX(B16-K_CALL,0)-FC_AMT*PREM_CALL -> 14200000 | H16: =TEXT(A16,"0%") -> 105%

Sheet Checks
A1: Model Validation Checks
A3: MODEL STATUS | B3: =IF(COUNTIF(F6:F13,"FAIL")=0,"PASS","FAIL") -> PASS
A5: Check | B5: Actual | C5: Expected | D5: Difference | E5: Tolerance | F5: Status | G5: Where to Fix
A6: Named input completeness | B6: =COUNT(FC_AMT,S0_in,F0_in,R_USD,R_FC,K_PUT,K_CALL,PREM_PUT,PREM_CALL,T_DAYS) -> 10 | C6: ='Notes & Assumptions'!B17 -> 10 | D6: =B6-C6 -> 0 | E6: ='Notes & Assumptions'!B18 -> 0 | F6: =IF(ABS(D6)<=E6,"PASS","FAIL") -> PASS | G6: Inputs!D6:D15
A7: Input boundaries | B7: =MIN(FC_AMT,S0_in,F0_in,K_PUT,K_CALL,T_DAYS,PREM_PUT,PREM_CALL) -> 0.017 | C7: =0 -> 0 | D7: =B7-C7 -> 0.017 | E7: ='Notes & Assumptions'!B18 -> 0 | F7: =IF(AND(FC_AMT>0,S0_in>0,F0_in>0,K_PUT>0,K_CALL>0,T_DAYS>0,PREM_PUT>=0,PREM_CALL>=0),"PASS","FAIL") -> PASS | G7: Inputs!D6:D15
A8: Forward calculation | B8: ='Forward Hedge'!B10 -> 13637500 | C8: =FC_AMT*F0_in -> 13637500 | D8: =B8-C8 -> 0 | E8: ='Notes & Assumptions'!B16 -> 0.01 | F8: =IF(ABS(D8)<=E8,"PASS","FAIL") -> PASS | G8: Forward Hedge!B10
A9: Covered-interest parity | B9: ='Money Market'!C11 -> 1.091 | C9: =F0_in -> 1.091 | D9: =B9-C9 -> 0 | E9: =ABS(C9)*'Notes & Assumptions'!B15 -> 0.005455 | F9: =IF(ABS(D9)<=E9,"PASS","FAIL") -> PASS | G9: Money Market!C11:C13
A10: Money-market reconciliation | B10: ='Money Market'!C9 -> 13637500 | C10: ='Forward Hedge'!B10 -> 13637500 | D10: =B10-C10 -> 0 | E10: =ABS(C10)*'Notes & Assumptions'!B15 -> 68187.5 | F10: =IF(ABS(D10)<=E10,"PASS","FAIL") -> PASS | G10: Money Market!C9
A11: Put-option floor | B11: =MIN(Sensitivity!F6:F16) -> 13162500 | C11: =FC_AMT*K_PUT-FC_AMT*PREM_PUT -> 13162500 | D11: =B11-C11 -> 0 | E11: ='Notes & Assumptions'!B16 -> 0.01 | F11: =IF(B11>=C11-E11,"PASS","FAIL") -> PASS | G11: Option Hedge / Sensitivity
A12: Sensitivity scenario count | B12: =COUNT(Sensitivity!B6:B16) -> 11 | C12: ='Notes & Assumptions'!B14 -> 11 | D12: =B12-C12 -> 0 | E12: ='Notes & Assumptions'!B18 -> 0 | F12: =IF(ABS(D12)<=E12,"PASS","FAIL") -> PASS | G12: Sensitivity!A6:G16
A13: Sensitivity endpoints | B13: =MAX(ABS(Sensitivity!B6-S0_in*'Notes & Assumptions'!B12),ABS(Sensitivity!B16-S0_in*('Notes & Assumptions'!B12+('Notes & Assumptions'!B14-1)*'Notes & Assumptions'!B13))) -> 0 | C13: =0 -> 0 | D13: =B13-C13 -> 0 | E13: ='Notes & Assumptions'!B19 -> 1e-06 | F13: =IF(ABS(D13)<=E13,"PASS","FAIL") -> PASS | G13: Sensitivity!B6:B16

Sheet Notes & Assumptions
A1: Notes & Assumptions
A4: Model Conventions and Control Assumptions
A5: Assumption | B5: Value | C5: Explanation
A6: Day-count basis | B6: ACT/360 | C6: Actual days divided by 360 for both currencies.
A7: Transaction costs | B7: Excluded | C7: Bid-ask spreads, fees, taxes, and commissions are excluded.
A8: Interest method | B8: Simple annual | C8: Rates are annualized and prorated over T_DAYS / 360.
A9: Option premium treatment | B9: Deducted upfront | C9: Premiums are deducted directly without financing.
A10: FX quote convention | B10: USD per EUR | C10: EUR/USD indicates the U.S. dollars received per euro.
A11: Stage 4 replacement | B11: Required | C11: All indicative market inputs must be replaced with live data.
A12: Sensitivity start | B12: 0.95 | C12: Starting settlement-rate multiplier.
A13: Sensitivity step | B13: 0.01 | C13: One-percentage-point multiplier step.
A14: Sensitivity scenarios | B14: 11 | C14: 95% through 105%, inclusive.
A15: Parity tolerance | B15: 0.005 | C15: Relative tolerance for parity and reconciliation checks.
A16: Currency tolerance | B16: 0.01 | C16: Rounding tolerance in USD.
A17: Expected named inputs | B17: 10 | C17: Required named-range count from the build contract.
A18: Exact-count tolerance | B18: 0 | C18: Counts must match exactly.
A19: Rate-formula tolerance | B19: 1e-06 | C19: Tolerance for sensitivity endpoint formulas.
A21: Build Notes
A22: The Stage 2 specification leaves S0_in, R_USD, R_FC, K_PUT, and K_CALL as TBD. Stage 3 therefore uses clearly labeled indicative values so every formula and validation check can run. Stage 4 must replace them with sourced live data.
A23: R_FC is calibrated to the indicative spot, USD rate, and assigned forward quote so the covered-interest-parity check can be demonstrated. It is not presented as a live market observation.
A24: The purchased call is included for build-contract completeness and as a reference payoff. It does not hedge the downside risk of a EUR receivable; the EUR put is the relevant protective option.
A26: Sources and Provenance
A27: Item | B27: Status | C27: Source | D27: As of | E27: Notes
A28: Assigned Scenario 3 | B28: Assigned | C28: https://github.com/adamwstauffer/shidler/blob/main/courses/International-Finance-And-Securities/projects/fx-hedging/scenarios.md | D28: 2026-08-08 | E28: EUR 12.5m receivable; 365 days; F0 1.0910; put premium 0.017; call premium 0.022.
A29: Stage 2 specification | B29: Committed | C29: https://github.com/timmy3-del/Timmy-Vuong/blob/main/docs/specs/2026-08-07-Vuong-tech-services-spec.md | D29: 2026-08-08 | E29: Workbook source specification.
A30: Stage 3 instructions | B30: Required | C30: https://adamwstauffer.github.io/ai-lms/fx-hedging-stage3.html | D30: 2026-08-08 | E30: Build contract and audit requirements.
